pysnap/__init__.py
pysnap/diff.py
pysnap/django.py
pysnap/error.py
pysnap/file.py
pysnap/formatter.py
pysnap/formatters.py
pysnap/generic_repr.py
pysnap/module.py
pysnap/nose.py
pysnap/pytest.py
pysnap/reporting.py
pysnap/snapshot.py
pysnap/sorted_dict.py
pysnap/unittest.py
snapshottest/__init__.py
snapshottest/diff.py
snapshottest/django.py
snapshottest/error.py
snapshottest/file.py
snapshottest/formatter.py
snapshottest/formatters.py
snapshottest/generic_repr.py
snapshottest/module.py
snapshottest/nose.py
snapshottest/pytest.py
snapshottest/reporting.py
snapshottest/snapshot.py
snapshottest/sorted_dict.py
snapshottest/unittest.py
pysnap-1.0.1.dist-info/LICENSE
pysnap-1.0.1.dist-info/METADATA
pysnap-1.0.1.dist-info/WHEEL
pysnap-1.0.1.dist-info/entry_points.txt
pysnap-1.0.1.dist-info/top_level.txt
pysnap-1.0.1.dist-info/RECORD
