Metadata-Version: 2.1
Name: pysnap
Version: 1.0.1
Summary: Snapshot Testing utils for Python
Home-page: https://github.com/yourbuddyconner/pysnap
Author: Conner Swann
Author-email: me@connerswann.me
License: MIT
Platform: UNKNOWN
Classifier: Development Status :: 3 - Alpha
Classifier: Framework :: Pytest
Classifier: Intended Audience :: Developers
Classifier: Operating System :: OS Independent
Classifier: Programming Language :: Python
Classifier: Programming Language :: Python :: 2
Classifier: Programming Language :: Python :: 2.7
Classifier: Programming Language :: Python :: 3
Classifier: Programming Language :: Python :: 3.4
Classifier: Programming Language :: Python :: 3.5
Classifier: Programming Language :: Python :: 3.6
Classifier: Topic :: Software Development :: Libraries
Requires-Dist: six (>=1.10.0)
Requires-Dist: termcolor
Provides-Extra: nose
Requires-Dist: nose ; extra == 'nose'
Provides-Extra: pytest
Requires-Dist: pytest ; extra == 'pytest'
Provides-Extra: test
Requires-Dist: six ; extra == 'test'
Requires-Dist: pytest (>=3.6.0) ; extra == 'test'
Requires-Dist: pytest-cov ; extra == 'test'
Requires-Dist: nose ; extra == 'test'
Requires-Dist: django (>=1.11.21) ; extra == 'test'
